pykaHFM/__init__.py
pykaHFM/data_loader.py
pykaHFM/data_transform.py
pykaHFM/factor_machine.py
pykaHFM/gradient_descent.py
pykaHFM/knowledge_base.py
pykaHFM-0.2.2.dist-info/METADATA
pykaHFM-0.2.2.dist-info/WHEEL
pykaHFM-0.2.2.dist-info/top_level.txt
pykaHFM-0.2.2.dist-info/RECORD
