Metadata-Version: 2.1
Name: pykaHFM
Version: 0.2.2
Summary: An implementation of kaHFM algorithm
Home-page: https://github.com/jirifilip/pykaHFM
Author: Jiří Filip
Author-email: j.f.ilip@seznam.cz
License: UNKNOWN
Keywords: pykaHFM
Platform: UNKNOWN
Requires-Dist: pandas
Requires-Dist: numpy
